pyfoma/__init__.py
pyfoma/algorithms.py
pyfoma/cfg.py
pyfoma/eliminate_flags.py
pyfoma/flag.py
pyfoma/fst.py
pyfoma/paradigm.py
pyfoma/py.typed
pyfoma/_private/__init__.py
pyfoma/_private/partition_refinement.py
pyfoma/_private/regexparse.py
pyfoma-1.0.7.dist-info/licenses/LICENSE
pyfoma-1.0.7.dist-info/METADATA
pyfoma-1.0.7.dist-info/WHEEL
pyfoma-1.0.7.dist-info/top_level.txt
pyfoma-1.0.7.dist-info/RECORD
