Metadata-Version: 2.4
Name: pyfoma
Version: 1.0.7
Summary: Python Finite-State Toolkit
Home-page: https://github.com/mhulden/pyfoma
Author: Mans Hulden
Author-email: mans.hulden@colorado.edu
Project-URL: Bug Tracker, https://github.com/mhulden/pyfoma/issues
Classifier: Programming Language :: Python :: 3
Classifier: License :: OSI Approved :: Apache Software License
Classifier: Operating System :: OS Independent
Requires-Python: >=3.6
License-File: LICENSE
Requires-Dist: IPython
Requires-Dist: graphviz
Dynamic: author
Dynamic: author-email
Dynamic: classifier
Dynamic: description
Dynamic: description-content-type
Dynamic: home-page
Dynamic: license-file
Dynamic: project-url
Dynamic: requires-dist
Dynamic: requires-python
Dynamic: summary
